extract_moodle/__init__.py
extract_moodle/main.py
extract_moodle-0.1.1.dist-info/METADATA
extract_moodle-0.1.1.dist-info/WHEEL
extract_moodle-0.1.1.dist-info/entry_points.txt
extract_moodle-0.1.1.dist-info/top_level.txt
extract_moodle-0.1.1.dist-info/RECORD
